{
    "metadata": {
        "NOMOR": "CP20DJFAJ003-2500954-A02",
        "PRODUCT CATEGORY ": "COOKING OIL REF DOC: APP-KC1102-20DJFAJ003-25-00001369",
        "BRAND ": "FORTUNE REF CP NO : Additional-CP20DJFAJ003-2500954",
        "CHANNEL ": "GT PERIODE CP: 07/03/2025 - 15/03/2025",
        "REGION ": "KC0011 - BMW HO JAKARTA GROUP OUTLET :",
        "SUB REGION ": "KC001102 - LAMPUNG",
        "DISTRIBUTOR ": "20DJFAJ003 - CV. Fajar Lestari Kotabumi",
        "PROMO TYPE ": "31. DISCOUNT PROMO - 31. DISCOUNT PROMO COMPENSATION :",
        "SUB PROMO TYPE ": "31C - STRATA DISCOUNT COST CATEGORY [ ] INCLUDE TRADING TERM [ ] EXCLUDE TRADING TERM [ ] OTB [ ] PF TIPE CP [X] CLAIM [ ] ON INVOICE [ ] PURCHASE TIPE CLAIM [ ] PRINCIPAL [X] DISTRIBUTOR CLAIM BASED [ ] SELLING - IN [X] SELLING - OUT",
        "MECHANISM": "'1. Strata '2. Dist klaim berdasarkan ketentuan '3. Auto PD DISCOUNT PROMOTION DISC % Additional Disc % CUT PRICE PRICE LIST SHARE SKU UOM RBP DIST STRATA RBP STORE RBP NET INC PPN SATP DIST % REG IOM OTH D 1 D 2 D 3 D 4 D 5 OTB PF FORTUNE PALM OIL BAG 17.200,00 - - - 17.200,00 ✔ 3,38 - - - - 0,00 0,00 16.618,64 0,25 18.400,57 PLP @1LT FORTUNE PALM OIL CTN6/PCH 36.200,00 - - - 36.200,00 ✔ 2,94 - - - - 0,00 0,00 35.135,72 0,00 39.000,65 PCH @2LT FORTUNE PALM OIL CTN12/PCH 18.430,00 - - - 18.430,00 ✔ 3,70 - - - - 0,00 0,00 17.748,09 0,00 19.700,38 PCH @1LT FORTUNE PALM OIL CTN6/PCH 32.800,00 - - - 32.800,00 ✔ 3,04 - - - - 0,00 0,00 31.802,88 0,00 35.301,20 PCH @1.8LT FORTUNE PALM OIL BAG 14.000,00 - - - 14.000,00 ✔ 3,23 - - - - 0,00 0,00 13.547,80 0,25 15.000,46 PLP @0.8LT FORTUNE PALM OIL CTN12/PCH 15.200,00 - - - 15.200,00 ✔ 4,58 - - - - 0,00 0,00 14.503,84 0,00 16.099,26 PCH @0.8LT STRATA DISCOUNT TABLE CUT PRICE SHARE SKU UOM MIN QTY / CTN DISC % RBP STORE OFF INV RBP NET INC PPN DIST % OTB PF '24 2,86 16.708,08 0,00 18.499,60 FORTUNE PALM OIL BAG - 0,25 PLP @1LT '72 3,38 16.618,64 0,00 18.400,57 '1/0 2,44 35.316,72 0,00 39.201,56 FORTUNE PALM OIL CTN6/PCH - - PCH @2LT '3/0 2,94 35.135,72 0,00 39.000,65 '1/0 3,21 17.838,40 0,00 19.800,62 FORTUNE PALM OIL CTN12/PCH - - PCH @1LT '3/0 3,70 17.748,09 0,00 19.700,38 '1/0 2,49 31.983,28 0,00 35.501,44 FORTUNE PALM OIL CTN6/PCH - - PCH @1.8LT '3/0 3,04 31.802,88 0,00 35.301,20 '24 2,59 13.637,40 0,00 15.099,67 FORTUNE PALM OIL BAG - 0,25 PLP @0.8LT '72 3,23 13.547,80 0,00 15.000,46 '1/0 3,98 14.595,04 0,00 16.200,49 FORTUNE PALM OIL CTN12/PCH - - PCH @0.8LT '3/0 4,58 14.503,84 0,00 16.099,26"
    },
    "tables": [
        [
            {
                "0": "REF DOC: APP-KC1102-20DJFAJ003-25-00001369"
            },
            {
                "0": "REF CP NO : Additional-CP20DJFAJ003-2500954"
            },
            {
                "0": "PERIODE CP: 07/03/2025 - 15/03/2025"
            }
        ],
        [
            {
                "0": "DISCOUNT PROMOTION",
                "1": null,
                "2": null,
                "3": null,
                "4": null,
                "5": null,
                "6": null,
                "7": null,
                "8": null,
                "9": null,
                "10": null,
                "11": null,
                "12": null,
                "13": null,
                "14": null,
                "15": null,
                "16": null,
                "17": null
            },
            {
                "0": "SKU",
                "1": "UOM",
                "2": "PRICE LIST\nSATP",
                "3": "DISC %",
                "4": null,
                "5": null,
                "6": "RBP DIST",
                "7": "STRATA",
                "8": "Additional Disc %",
                "9": null,
                "10": null,
                "11": null,
                "12": null,
                "13": "CUT PRICE",
                "14": null,
                "15": "RBP STORE",
                "16": "SHARE\nDIST %",
                "17": "RBP NET INC PPN"
            },
            {
                "0": null,
                "1": null,
                "2": null,
                "3": "REG",
                "4": "IOM",
                "5": "OTH",
                "6": null,
                "7": null,
                "8": "D 1",
                "9": "D 2",
                "10": "D 3",
                "11": "D 4",
                "12": "D 5",
                "13": "OTB",
                "14": "PF",
                "15": null,
                "16": null,
                "17": null
            },
            {
                "0": "FORTUNE PALM OIL\nPLP @1LT",
                "1": "BAG",
                "2": "17.200,00",
                "3": "-",
                "4": "-",
                "5": "-",
                "6": "17.200,00",
                "7": "✔",
                "8": "3,38",
                "9": "-",
                "10": "-",
                "11": "-",
                "12": "-",
                "13": "0,00",
                "14": "0,00",
                "15": "16.618,64",
                "16": "0,25",
                "17": "18.400,57"
            },
            {
                "0": "FORTUNE PALM OIL\nPCH @2LT",
                "1": "CTN6/PCH",
                "2": "36.200,00",
                "3": "-",
                "4": "-",
                "5": "-",
                "6": "36.200,00",
                "7": "✔",
                "8": "2,94",
                "9": "-",
                "10": "-",
                "11": "-",
                "12": "-",
                "13": "0,00",
                "14": "0,00",
                "15": "35.135,72",
                "16": "0,00",
                "17": "39.000,65"
            },
            {
                "0": "FORTUNE PALM OIL\nPCH @1LT",
                "1": "CTN12/PCH",
                "2": "18.430,00",
                "3": "-",
                "4": "-",
                "5": "-",
                "6": "18.430,00",
                "7": "✔",
                "8": "3,70",
                "9": "-",
                "10": "-",
                "11": "-",
                "12": "-",
                "13": "0,00",
                "14": "0,00",
                "15": "17.748,09",
                "16": "0,00",
                "17": "19.700,38"
            },
            {
                "0": "FORTUNE PALM OIL\nPCH @1.8LT",
                "1": "CTN6/PCH",
                "2": "32.800,00",
                "3": "-",
                "4": "-",
                "5": "-",
                "6": "32.800,00",
                "7": "✔",
                "8": "3,04",
                "9": "-",
                "10": "-",
                "11": "-",
                "12": "-",
                "13": "0,00",
                "14": "0,00",
                "15": "31.802,88",
                "16": "0,00",
                "17": "35.301,20"
            },
            {
                "0": "FORTUNE PALM OIL\nPLP @0.8LT",
                "1": "BAG",
                "2": "14.000,00",
                "3": "-",
                "4": "-",
                "5": "-",
                "6": "14.000,00",
                "7": "✔",
                "8": "3,23",
                "9": "-",
                "10": "-",
                "11": "-",
                "12": "-",
                "13": "0,00",
                "14": "0,00",
                "15": "13.547,80",
                "16": "0,25",
                "17": "15.000,46"
            },
            {
                "0": "FORTUNE PALM OIL\nPCH @0.8LT",
                "1": "CTN12/PCH",
                "2": "15.200,00",
                "3": "-",
                "4": "-",
                "5": "-",
                "6": "15.200,00",
                "7": "✔",
                "8": "4,58",
                "9": "-",
                "10": "-",
                "11": "-",
                "12": "-",
                "13": "0,00",
                "14": "0,00",
                "15": "14.503,84",
                "16": "0,00",
                "17": "16.099,26"
            }
        ],
        [
            {
                "0": "STRATA DISCOUNT TABLE",
                "1": null,
                "2": null,
                "3": null,
                "4": null,
                "5": null,
                "6": null,
                "7": null,
                "8": null
            },
            {
                "0": "SKU",
                "1": "UOM",
                "2": "MIN QTY / CTN",
                "3": "DISC %",
                "4": "RBP STORE OFF INV",
                "5": "CUT PRICE",
                "6": null,
                "7": "SHARE\nDIST %",
                "8": "RBP NET INC PPN"
            },
            {
                "0": null,
                "1": null,
                "2": null,
                "3": null,
                "4": null,
                "5": "OTB",
                "6": "PF",
                "7": null,
                "8": null
            },
            {
                "0": "FORTUNE PALM OIL\nPLP @1LT",
                "1": "BAG",
                "2": "'24",
                "3": "2,86",
                "4": "16.708,08",
                "5": "0,00",
                "6": "-",
                "7": "0,25",
                "8": "18.499,60"
            },
            {
                "0": null,
                "1": null,
                "2": "'72",
                "3": "3,38",
                "4": "16.618,64",
                "5": "0,00",
                "6": null,
                "7": null,
                "8": "18.400,57"
            },
            {
                "0": "FORTUNE PALM OIL\nPCH @2LT",
                "1": "CTN6/PCH",
                "2": "'1/0",
                "3": "2,44",
                "4": "35.316,72",
                "5": "0,00",
                "6": "-",
                "7": "-",
                "8": "39.201,56"
            },
            {
                "0": null,
                "1": null,
                "2": "'3/0",
                "3": "2,94",
                "4": "35.135,72",
                "5": "0,00",
                "6": null,
                "7": null,
                "8": "39.000,65"
            },
            {
                "0": "FORTUNE PALM OIL\nPCH @1LT",
                "1": "CTN12/PCH",
                "2": "'1/0",
                "3": "3,21",
                "4": "17.838,40",
                "5": "0,00",
                "6": "-",
                "7": "-",
                "8": "19.800,62"
            },
            {
                "0": null,
                "1": null,
                "2": "'3/0",
                "3": "3,70",
                "4": "17.748,09",
                "5": "0,00",
                "6": null,
                "7": null,
                "8": "19.700,38"
            },
            {
                "0": "FORTUNE PALM OIL\nPCH @1.8LT",
                "1": "CTN6/PCH",
                "2": "'1/0",
                "3": "2,49",
                "4": "31.983,28",
                "5": "0,00",
                "6": "-",
                "7": "-",
                "8": "35.501,44"
            },
            {
                "0": null,
                "1": null,
                "2": "'3/0",
                "3": "3,04",
                "4": "31.802,88",
                "5": "0,00",
                "6": null,
                "7": null,
                "8": "35.301,20"
            },
            {
                "0": "FORTUNE PALM OIL\nPLP @0.8LT",
                "1": "BAG",
                "2": "'24",
                "3": "2,59",
                "4": "13.637,40",
                "5": "0,00",
                "6": "-",
                "7": "0,25",
                "8": "15.099,67"
            },
            {
                "0": null,
                "1": null,
                "2": "'72",
                "3": "3,23",
                "4": "13.547,80",
                "5": "0,00",
                "6": null,
                "7": null,
                "8": "15.000,46"
            },
            {
                "0": "FORTUNE PALM OIL\nPCH @0.8LT",
                "1": "CTN12/PCH",
                "2": "'1/0",
                "3": "3,98",
                "4": "14.595,04",
                "5": "0,00",
                "6": "-",
                "7": "-",
                "8": "16.200,49"
            },
            {
                "0": null,
                "1": null,
                "2": "'3/0",
                "3": "4,58",
                "4": "14.503,84",
                "5": "0,00",
                "6": null,
                "7": null,
                "8": "16.099,26"
            }
        ],
        [
            {
                "0": "SKU",
                "1": "UOM",
                "2": "RBP DIST",
                "3": "PRODUCT PROMOTION",
                "4": null,
                "5": null,
                "6": null,
                "7": null,
                "8": null,
                "9": null,
                "10": null
            },
            {
                "0": null,
                "1": null,
                "2": null,
                "3": "MIX\nITEM",
                "4": "STRATA",
                "5": "SKU BONUS",
                "6": "DESCRIPTION",
                "7": "Price\n(CBP/RBP/\nDBP/Cost)",
                "8": "UOM",
                "9": "QTY IN\nPCS",
                "10": "TOTAL BUDGET"
            },
            {
                "0": "FORTUNE PALM OIL\nPLP @1LT",
                "1": "BAG",
                "2": "17.200,00",
                "3": "",
                "4": "",
                "5": "",
                "6": "",
                "7": "0,00",
                "8": "",
                "9": "0",
                "10": "0,00"
            },
            {
                "0": "FORTUNE PALM OIL\nPCH @2LT",
                "1": "CTN6/PCH",
                "2": "36.200,00",
                "3": "",
                "4": "",
                "5": "",
                "6": "",
                "7": "0,00",
                "8": "",
                "9": "0",
                "10": "0,00"
            },
            {
                "0": "FORTUNE PALM OIL\nPCH @1LT",
                "1": "CTN12/PCH",
                "2": "18.430,00",
                "3": "",
                "4": "",
                "5": "",
                "6": "",
                "7": "0,00",
                "8": "",
                "9": "0",
                "10": "0,00"
            },
            {
                "0": "FORTUNE PALM OIL\nPCH @1.8LT",
                "1": "CTN6/PCH",
                "2": "32.800,00",
                "3": "",
                "4": "",
                "5": "",
                "6": "",
                "7": "0,00",
                "8": "",
                "9": "0",
                "10": "0,00"
            },
            {
                "0": "FORTUNE PALM OIL\nPLP @0.8LT",
                "1": "BAG",
                "2": "14.000,00",
                "3": "",
                "4": "",
                "5": "",
                "6": "",
                "7": "0,00",
                "8": "",
                "9": "0",
                "10": "0,00"
            },
            {
                "0": "FORTUNE PALM OIL\nPCH @0.8LT",
                "1": "CTN12/PCH",
                "2": "15.200,00",
                "3": "",
                "4": "",
                "5": "",
                "6": "",
                "7": "0,00",
                "8": "",
                "9": "0",
                "10": "0,00"
            }
        ],
        [
            {
                "0": "SKU",
                "1": "SALES COMITMENT",
                "2": null,
                "3": "TOTAL DISCOUNT",
                "4": "TOTAL PRODUCT PROMO",
                "5": "TOTAL OTB",
                "6": "TOTAL PF",
                "7": "TOTAL EST BUDGET\nPROMO"
            },
            {
                "0": null,
                "1": "QTY IN CTN",
                "2": "VALUE",
                "3": null,
                "4": null,
                "5": null,
                "6": null,
                "7": null
            },
            {
                "0": "FORTUNE PALM OIL\nPLP @1LT",
                "1": "6.000",
                "2": "99.711.840,00",
                "3": "3.492.000,00",
                "4": "0,00",
                "5": "-",
                "6": "-",
                "7": "3.492.000,00"
            },
            {
                "0": "FORTUNE PALM OIL\nPCH @2LT",
                "1": "250/0",
                "2": "52.703.580,00",
                "3": "1.597.500,00",
                "4": "0,00",
                "5": "-",
                "6": "-",
                "7": "1.597.500,00"
            },
            {
                "0": "FORTUNE PALM OIL\nPCH @1LT",
                "1": "100/0",
                "2": "21.297.708,00",
                "3": "818.400,00",
                "4": "0,00",
                "5": "-",
                "6": "-",
                "7": "818.400,00"
            },
            {
                "0": "FORTUNE PALM OIL\nPCH @1.8LT",
                "1": "0/0",
                "2": "0,00",
                "3": "0,00",
                "4": "0,00",
                "5": "-",
                "6": "-",
                "7": "0,00"
            },
            {
                "0": "FORTUNE PALM OIL\nPLP @0.8LT",
                "1": "0",
                "2": "0,00",
                "3": "0,00",
                "4": "0,00",
                "5": "-",
                "6": "-",
                "7": "0,00"
            },
            {
                "0": "FORTUNE PALM OIL\nPCH @0.8LT",
                "1": "0/0",
                "2": "0,00",
                "3": "0,00",
                "4": "0,00",
                "5": "-",
                "6": "-",
                "7": "0,00"
            }
        ]
    ]
}